LICENSE
README.rst
setup.py
dde_dnms/__init__.py
dde_dnms/api_client.py
dde_dnms/config.py
dde_dnms/exceptions.py
dde_dnms/odps_client.py
dde_dnms/validators.py
dde_dnms/version.py
dde_dnms.egg-info/PKG-INFO
dde_dnms.egg-info/SOURCES.txt
dde_dnms.egg-info/dependency_links.txt
dde_dnms.egg-info/requires.txt
dde_dnms.egg-info/top_level.txt