Metadata-Version: 2.1
Name: dde-dnms
Version: 0.1
Summary: 给希望使用deep-time.org中注册数据用户提供的sdk
Author: suncong
Author-email: csun@elemparticle.com
License: BSD License
License-File: LICENSE
